LICENSE
README.md
setup.py
src/ira_auth_m2m/__init__.py
src/ira_auth_m2m/auth.py
src/ira_auth_m2m_client.egg-info/PKG-INFO
src/ira_auth_m2m_client.egg-info/SOURCES.txt
src/ira_auth_m2m_client.egg-info/dependency_links.txt
src/ira_auth_m2m_client.egg-info/requires.txt
src/ira_auth_m2m_client.egg-info/top_level.txt