Metadata-Version: 2.1
Name: ira-auth-m2m-client
Version: 0.1.0
Summary: IraAuthM2M authenticates an application by IraAuth so that it can access APIs protected by IraAuth
Home-page: https://github.com/epicira/ira-auth-m2m-client
Author: Daryl Correa (Epicode)
Author-email: daryl.correa@epicode.in
License: MIT
Project-URL: Bug Tracker, https://github.com/epicira/ira-auth-m2m-client/issues
License-File: LICENSE
